LICENSE
README.md
setup.py
common_stats/__init__.py
common_stats/statistics.py
common_stats_vishishta.egg-info/PKG-INFO
common_stats_vishishta.egg-info/SOURCES.txt
common_stats_vishishta.egg-info/dependency_links.txt
common_stats_vishishta.egg-info/requires.txt
common_stats_vishishta.egg-info/top_level.txt