Metadata-Version: 2.1
Name: common-stats-vishishta
Version: 0.0.1
Summary: A simple library for basic statistical calculations
Author: Vish
Author-email: pVishishta@gmail.com
License: MIT
Requires-Python: >=3.7
License-File: LICENSE
